boopy/__init__.py
boopy/interest_rate.py
boopy/helpers/__init__.py
boopy/helpers/deposit_helper.py
boopy/helpers/fra_helper.py
boopy/helpers/interest_rate_helper.py
boopy/helpers/swap_helper.py
boopy/time/__init__.py
boopy/time/frequency.py
boopy/time/period.py
boopy/time/schedule.py
boopy-0.1.1.dist-info/LICENSE.txt
boopy-0.1.1.dist-info/METADATA
boopy-0.1.1.dist-info/WHEEL
boopy-0.1.1.dist-info/top_level.txt
boopy-0.1.1.dist-info/RECORD
